.gitignore
LICENSE
README.md
Untitled.ipynb
Untitled1.ipynb
Untitled2.ipynb
cli_example.py
data.csv
python_example.py
requirements.txt
res.csv
setup.cfg
setup.py
mssibyl/__init__.py
mssibyl.egg-info/PKG-INFO
mssibyl.egg-info/SOURCES.txt
mssibyl.egg-info/dependency_links.txt
mssibyl.egg-info/requires.txt
mssibyl.egg-info/top_level.txt
mssibyl/datasets/__init__.py
mssibyl/datasets/utils.py
mssibyl/models/__init__.py
mssibyl/models/base.py
mssibyl/trainer/__init__.py
mssibyl/trainer/base_trainer.py
mssibyl/utils/__init__.py