Metadata-Version: 2.1
Name: mssibyl
Version: 0.1.1.dev0
Summary: Time Series Forecasting Tool for Machine Learning Researchers with Nerual Process
Home-page: UNKNOWN
Author: More Zhou
Author-email: jinyzho@microsoft.com
License: MIT
Keywords: time series forecasting,deep learning,pytorch
Platform: UNKNOWN
Classifier: Development Status :: 3 - Alpha
Classifier: Intended Audience :: Developers
Classifier: Topic :: Software Development :: Build Tools
Classifier: Programming Language :: Python :: 3.6
Classifier: Programming Language :: Python :: 3.7
Classifier: Programming Language :: Python :: 3.8
